proximal/__init__.py
proximal/algorithms/__init__.py
proximal/algorithms/absorb.py
proximal/algorithms/admm.py
proximal/algorithms/equil.py
proximal/algorithms/half_quadratic_splitting.py
proximal/algorithms/invert.py
proximal/algorithms/linearized_admm.py
proximal/algorithms/merge.py
proximal/algorithms/pock_chambolle.py
proximal/algorithms/problem.py
proximal/halide/__init__.py
proximal/halide/halide.py
proximal/halide/meson.build
proximal/halide/src/A_conv.cpp
proximal/halide/src/A_dot_prod.cpp
proximal/halide/src/A_grad.cpp
proximal/halide/src/A_mask.cpp
proximal/halide/src/A_norm_L2.cpp
proximal/halide/src/A_warp.cpp
proximal/halide/src/At_conv.cpp
proximal/halide/src/At_grad.cpp
proximal/halide/src/At_mask.cpp
proximal/halide/src/At_warp.cpp
proximal/halide/src/fft2_r2c.cpp
proximal/halide/src/ifft2_c2r.cpp
proximal/halide/src/prox_FANN.cpp
proximal/halide/src/prox_IsoL1.cpp
proximal/halide/src/prox_L1.cpp
proximal/halide/src/prox_NLM.cpp
proximal/halide/src/prox_Poisson.cpp
proximal/halide/src/core/image_formation.h
proximal/halide/src/core/prior_transforms.h
proximal/halide/src/core/prox_operators.h
proximal/halide/src/core/prox_operators_image_form.h
proximal/halide/src/core/vars.h
proximal/halide/src/external/external_FANN.cpp
proximal/halide/src/external/external_NLM.cpp
proximal/halide/src/external/static_image.h
proximal/halide/src/fft/complex.h
proximal/halide/src/fft/fft.cpp
proximal/halide/src/fft/fft.h
proximal/halide/src/fft/funct.h
proximal/halide/subprojects/halide.wrap
proximal/halide/subprojects/pybind11.wrap
proximal/halide/subprojects/packagefiles/halide/meson.build
proximal/lin_ops/__init__.py
proximal/lin_ops/black_box.py
proximal/lin_ops/comp_graph.py
proximal/lin_ops/constant.py
proximal/lin_ops/conv.py
proximal/lin_ops/conv_nofft.py
proximal/lin_ops/edge.py
proximal/lin_ops/grad.py
proximal/lin_ops/hstack.py
proximal/lin_ops/lin_op.py
proximal/lin_ops/mul_color.py
proximal/lin_ops/mul_elemwise.py
proximal/lin_ops/pxwise_matrixmult.py
proximal-0.1.7.dist-info/LICENSE
proximal-0.1.7.dist-info/METADATA
proximal-0.1.7.dist-info/WHEEL
proximal-0.1.7.dist-info/top_level.txt
proximal-0.1.7.dist-info/RECORD
