Metadata-Version: 2.1
Name: proximal
Version: 0.1.7
Summary: UNKNOWN
Home-page: http://github.com/comp-imaging/ProxImaL/
Author: UNKNOWN
Author-email: UNKNOWN
License: UNKNOWN
Platform: UNKNOWN
Requires-Dist: numpy (>=1.9)
Requires-Dist: scipy (>=0.15)
Requires-Dist: numexpr
Requires-Dist: Pillow
Requires-Dist: meson (>=0.54)
